{"CMIG4": {"LPA": "2,27", "VPA": "9,95", "Div Yeld": "11,12%"}, "BBSE3": {"LPA": "4,46", "VPA": "5,25", "Div Yeld": "12,99%"}, "TAEE11": {"LPA": "5,20", "VPA": "22,10", "Div Yeld": "8,01%"}, "BBAS3": {"LPA": "3,27", "VPA": "31,76", "Div Yeld": "7,81%"}, "DIRR3": {"LPA": "1,33", "VPA": "4,23", "Div Yeld": "6,79%"}, "ITSA4": {"LPA": "1,41", "VPA": "8,15", "Div Yeld": "8,72%"}, "BBDC4": {"LPA": "1,98", "VPA": "16,43", "Div Yeld": "8,68%"}, "CPLE6": {"LPA": "1,02", "VPA": "8,58", "Div Yeld": "6,34%"}, "PETR4": {"LPA": "6,00", "VPA": "30,97", "Div Yeld": "16,45%"}, "POMO4": {"LPA": "1,06", "VPA": "3,67", "Div Yeld": "6,90%"}, "CURY3": {"LPA": "2,69", "VPA": "4,56", "Div Yeld": "6,44%"}, "BRAP4": {"LPA": "2,75", "VPA": "22,31", "Div Yeld": "11,93%"}, "VALE3": {"LPA": "6,38", "VPA": "47,19", "Div Yeld": "7,96%"}, "CMIN3": {"LPA": "0,40", "VPA": "1,68", "Div Yeld": "15,04%"}, "MRFG3": {"LPA": "1,97", "VPA": "1,97", "Div Yeld": "28,87%"}, "CXSE3": {"LPA": "1,44", "VPA": "4,44", "Div Yeld": "7,95%"}, "PSSA3": {"LPA": "4,83", "VPA": "22,40", "Div Yeld": "4,99%"}, "EQTL3": {"LPA": "2,91", "VPA": "22,30", "Div Yeld": "2,12%"}, "ABEV3": {"LPA": "0,94", "VPA": "5,87", "Div Yeld": "8,47%"}, "CPFE3": {"LPA": "4,69", "VPA": "18,64", "Div Yeld": "7,19%"}, "ITSA3": {"LPA": "1,41", "VPA": "8,15", "Div Yeld": "8,69%"}, "RADL3": {"LPA": "0,71", "VPA": "3,88", "Div Yeld": "2,25%"}, "B3SA3": {"LPA": "0,91", "VPA": "3,75", "Div Yeld": "2,08%"}, "WEGE3": {"LPA": "1,53", "VPA": "5,29", "Div Yeld": "2,01%"}, "EGIE3": {"LPA": "3,69", "VPA": "15,09", "Div Yeld": "5,05%"}}